fastr/__init__.py
fastr/exceptions.py
fastr/globals.py
fastr/version.py
fastr/versioninfo
fastr/abc/basemanager.py
fastr/abc/baseplugin.py
fastr/abc/basepluginmanager.py
fastr/abc/serializable.py
fastr/abc/updateable.py
fastr/api/__init__.py
fastr/core/__init__.py
fastr/core/cardinality.py
fastr/core/dimension.py
fastr/core/interface.py
fastr/core/ioplugin.py
fastr/core/provenance.py
fastr/core/resourcelimit.py
fastr/core/samples.py
fastr/core/target.py
fastr/core/tool.py
fastr/core/version.py
fastr/core/vfs.py
fastr/core/test/__init__.py
fastr/core/test/test_datatypemanager.py
fastr/core/test/test_dimension.py
fastr/core/test/test_samples.py
fastr/core/test/test_tool.py
fastr/core/test/test_version.py
fastr/core/test/test_vfs.py
fastr/data/__init__.py
fastr/data/url.py
fastr/datatypes/__init__.py
fastr/examples/__generate_reference__.py
fastr/examples/__init__.py
fastr/examples/add_ints.py
fastr/examples/add_ints_missing.py
fastr/examples/add_ints_s3.py
fastr/examples/advanced_linking.py
fastr/examples/auto_prefix.py
fastr/examples/chunk_test.py
fastr/examples/collapse.py
fastr/examples/collapse_expand.py
fastr/examples/cross_validation.py
fastr/examples/elastix_nipype.py
fastr/examples/envvar.py
fastr/examples/expand.py
fastr/examples/failing_macro.py
fastr/examples/failing_missing_macro.py
fastr/examples/failing_network.py
fastr/examples/failing_network_missing.py
fastr/examples/filecopy.py
fastr/examples/input_groups.py
fastr/examples/macro_node.py
fastr/examples/macro_node2.py
fastr/examples/shift_links.py
fastr/examples/source_sink.py
fastr/examples/via_file_argument.py
fastr/examples/data/hello.txt
fastr/examples/data/add_ints/value
fastr/examples/data/add_ints/values
fastr/examples/data/add_ints/values_duplicate
fastr/examples/data/images/mrwhite.mhd
fastr/examples/data/images/mrwhite.raw
fastr/examples/data/images/mrwhite_duplicate.mhd
fastr/examples/data/images/mrwhite_duplicate.raw
fastr/examples/data/reference/add_ints_0.0/__fastr_network__.json
fastr-3.4.0.dist-info/LICENSE
fastr-3.4.0.dist-info/METADATA
fastr-3.4.0.dist-info/WHEEL
fastr-3.4.0.dist-info/entry_points.txt
fastr-3.4.0.dist-info/top_level.txt
fastr-3.4.0.dist-info/RECORD
