Metadata-Version: 2.1
Name: fastr
Version: 3.4.0
Summary: Workflow creation and batch execution environment.
Home-page: https://gitlab.com/radiology/infrastructure/fastr
Author: H.C. Achterberg, M. Koek
Author-email: hakim.achterberg@gmail.com
License: Apache License 2.0
Classifier: Development Status :: 4 - Beta
Classifier: Intended Audience :: Developers
Classifier: Intended Audience :: Science/Research
Classifier: Intended Audience :: Healthcare Industry
Classifier: Intended Audience :: Information Technology
Classifier: Intended Audience :: Education
Classifier: License :: OSI Approved :: Apache Software License
Classifier: Natural Language :: English
Classifier: Operating System :: OS Independent
Classifier: Programming Language :: Python :: 3.6
Classifier: Programming Language :: Python :: 3.7
Classifier: Programming Language :: Python :: 3.8
Classifier: Programming Language :: Python :: 3.9
Classifier: Programming Language :: Python :: 3 :: Only
Classifier: Topic :: Scientific/Engineering :: Information Analysis
Classifier: Topic :: System :: Distributed Computing
Classifier: Topic :: System :: Logging
Classifier: Topic :: Utilities
Requires-Python: >=3.6
License-File: LICENSE
Requires-Dist: bidict >=0.18.0
Requires-Dist: colorama >=0.3.7
Requires-Dist: distro ==1.3.0
Requires-Dist: enum-compat
Requires-Dist: isodate >=0.5.4
Requires-Dist: jsonpickle >=0.9.5
Requires-Dist: jsonschema <4.0,>=3.0.0
Requires-Dist: GitPython >=3.1.3
Requires-Dist: graphviz >=0.8
Requires-Dist: redbaron >=0.9.2
Requires-Dist: sympy >=1.0
Requires-Dist: psutil >=3.1.0
Requires-Dist: PyYAML >=5.1
Requires-Dist: requests >=2.13.0
Requires-Dist: prov >=1.5.0
Requires-Dist: xnat <1.0.0,>=0.4.3
Requires-Dist: yarl >=1.7.0
